extendedsearch/__init__.py
extendedsearch/backend.py
extendedsearch/backends.py
extendedsearch/commands.py
extendedsearch/errors.py
extendedsearch/index.py
extendedsearch/models.py
extendedsearch/query.py
extendedsearch/settings.py
extendedsearch/signal_handlers.py
extendedsearch/utils.py
wagtail_extendedsearch-1.0.6.dist-info/LICENSE
wagtail_extendedsearch-1.0.6.dist-info/METADATA
wagtail_extendedsearch-1.0.6.dist-info/WHEEL
wagtail_extendedsearch-1.0.6.dist-info/namespace_packages.txt
wagtail_extendedsearch-1.0.6.dist-info/top_level.txt
wagtail_extendedsearch-1.0.6.dist-info/RECORD
