Metadata-Version: 2.1
Name: wagtail-extendedsearch
Version: 1.0.6
Summary: Add some more functionality to the wagtail elasticsearch search backend
Home-page: https://github.com/specialunderwear/wagtail-extendedsearch
Author: Lars van de Kerkhof
Author-email: no@way.why
License: GPL v2.1
Platform: UNKNOWN
Requires-Dist: setuptools
Requires-Dist: wagtail
Provides-Extra: test
